{
    "id": "2026-04-30-custom-why-did-homelander-kill-firecracker",
    "date": "2026-04-30",
    "title": "Homelander's Deadly Rage",
    "excerpt": "Homelander's ego explodes, killing Firecracker!",
    "persona": "BINGER",
    "category": "general",
    "tags": [
        "why",
        "did",
        "homelander",
        "kill",
        "firecracker"
    ],
    "thumbnail": null,
    "tmdb_ids": [],
    "readTimeMinutes": 3,
    "content": "<h1>Unpacking Homelander's Deadly Outburst</h1>\n      <p>Episode 1 of The Boys sets the stage for Homelander's rage issues, culminating in Firecracker's tragic death in episode 5. This incident is a symptom of a larger problem - the toxic culture of The Seven and the corrupt system that enables them. The show masterfully weaves together themes of toxic masculinity, celebrity culture, and the dangers of unchecked power, making it a thought-provoking watch.</p>\n      <p>The Boys is an unflinching critique of the darker aspects of human nature, with Homelander's actions serving as a prime example. The cast's chemistry is undeniable, and their character development is both nuanced and compelling. As the series progresses, it becomes clear that Homelander's actions are driven by a toxic mix of ego, insecurity, and entitlement, festering beneath the surface.</p>\n      <h2>The Incident: A Turning Point</h2>\n      <p>Firecracker's joke about Homelander's sexual prowess in episode 5 sparks a deadly response, highlighting the consequences of toxic masculinity. This pivotal moment marks a turning point in the series, as the characters' reactions and motivations are put to the test. Vought International's response - or lack thereof - underscores the corrupt system that enables The Seven, prioritizing their brand and reputation over accountability.</p>\n      <p>As the story unfolds, the characters' relationships and alliances are strained, leading to a deeper exploration of their moral compasses. Annie (Starlight) grapples with the moral implications of being part of The Seven, while Hughie's determination to take them down intensifies. Billy Butcher, meanwhile, sees an opportunity to exploit the situation, furthering his own agenda.</p>\n      <h2>Aftermath and Character Reactions</h2>\n      <p>The aftermath of Firecracker's death is a nuanced exploration of the characters' reactions and motivations. Hughie's horror and Billy's opportunism are contrasted with Annie's moral struggles, showcasing the cast's impressive chemistry. As the series delves deeper into the characters' psyches, it becomes clear that Homelander's actions have far-reaching consequences, affecting not only The Seven but also those around them.</p>\n      <p>The show's pacing expertly balances action, suspense, and character development, creating emotional payoff and investing viewers in the characters' journeys. The Boys' creators have crafted a compelling narrative that's both thought-provoking and entertaining, making it an absolute comfort watch.</p>\n      <h2>Themes and Social Commentary</h2>\n      <p>The Boys tackles a range of themes, including toxic masculinity, celebrity culture, and the dangers of unchecked power. Homelander's character serves as a prime example of these themes, with his actions driven by a toxic mix of ego, insecurity, and entitlement. The show's creators have woven these themes throughout the narrative, creating a nuanced and thought-provoking exploration of the human condition.</p>\n      <p>The series' use of social commentary is also noteworthy, with the corrupt system enabling The Seven serving as a commentary on the dangers of unchecked power and the importance of accountability. The show's creators have done an excellent job of crafting a narrative that's both entertaining and thought-provoking, making The Boys a must-watch for fans of superhero satire.</p>\n      <h2>The Verdict</h2>\n      <p>Homelander's actions are a symptom of a larger problem - the toxic culture of The Seven and the corrupt system that enables them. The Boys is a show that masterfully explores the darker aspects of human nature, with Homelander's character serving as a prime example. With its impressive cast chemistry, nuanced character development, and thought-provoking themes, The Boys is an absolute comfort watch that's not to be missed.</p>\n      <p>I'd give The Boys a solid 9/10 for its handling of this concept. The show's creators have done an excellent job of crafting a compelling narrative that's both thought-provoking and entertaining. If you haven't checked it out yet, you owe it to yourself to give it a try - just be prepared for a wild ride full of twists and turns.</p>\n      <h2>Watch/Read Next</h2>\n      <p>If you're a fan of The Boys, you might also enjoy Invincible, another show that explores the darker side of superhero culture. You might also enjoy The Umbrella Academy, a show that follows a dysfunctional family of superheroes as they try to uncover the truth about their past. Finally, if you're looking for something a bit more lighthearted, you might enjoy Titans, a show that follows a team of young superheroes as they navigate the challenges of being a hero.</p>",
    "link": "/blog.html?id=2026-04-30-custom-why-did-homelander-kill-firecracker"
}