[
    {
        "id": "2026-04-24-k-dramas",
        "date": "2026-04-24",
        "title": "K-Drama Frenzy",
        "category": "korean",
        "excerpt": "Explore the latest K-Dramas",
        "link": "/blog.html?id=2026-04-24-k-dramas"
    },
    {
        "id": "2026-04-24-sci-fi-thrillers",
        "date": "2026-04-24",
        "title": "5 Epic Sci-Fi Thrillers",
        "category": "movies",
        "excerpt": "Mind-blowing Sci-Fi Thrillers to binge now!",
        "link": "/blog.html?id=2026-04-24-sci-fi-thrillers"
    },
    {
        "id": "2026-04-22-k-dramas",
        "date": "2026-04-22",
        "title": "K-Drama Frenzy",
        "category": "korean",
        "excerpt": "Binge the best K-Dramas of 2025",
        "link": "/blog.html?id=2026-04-22-k-dramas"
    },
    {
        "id": "2026-04-22-sci-fi-thrillers",
        "date": "2026-04-22",
        "title": "Sci-Fi Thrill Ride",
        "category": "movies",
        "excerpt": "Mind-bending sci-fi thrillers to keep you on the edge",
        "link": "/blog.html?id=2026-04-22-sci-fi-thrillers"
    },
    {
        "id": "2026-04-21-k-dramas",
        "date": "2026-04-21",
        "title": "K-Drama Fix",
        "category": "korean",
        "excerpt": "5 addictive K-Dramas with insane cast chemistry",
        "link": "/blog.html?id=2026-04-21-k-dramas"
    },
    {
        "id": "2026-04-21-sci-fi-thrillers",
        "date": "2026-04-21",
        "title": "5 Sci-Fi Thrillers",
        "category": "movies",
        "excerpt": "5 heart-pumping sci-fi thrillers",
        "link": "/blog.html?id=2026-04-21-sci-fi-thrillers"
    },
    {
        "id": "2026-04-19-k-dramas",
        "date": "2026-04-19",
        "title": "K-Drama Frenzy",
        "category": "korean",
        "excerpt": "5 new K-Drama shows to binge",
        "link": "/blog.html?id=2026-04-19-k-dramas"
    },
    {
        "id": "2026-04-19-sci-fi-thrillers",
        "date": "2026-04-19",
        "title": "Sci-Fi Thrillers 2026",
        "category": "movies",
        "excerpt": "Discover the best sci-fi thrillers of 2026",
        "link": "/blog.html?id=2026-04-19-sci-fi-thrillers"
    },
    {
        "id": "2026-04-18-k-dramas",
        "date": "2026-04-18",
        "title": "K-Drama Frenzy",
        "category": "korean",
        "excerpt": "Top K-Drama picks and in-depth analysis",
        "link": "/blog.html?id=2026-04-18-k-dramas"
    },
    {
        "id": "2026-04-18-sci-fi-thrillers",
        "date": "2026-04-18",
        "title": "2026 Sci-Fi Thrillers",
        "category": "movies",
        "excerpt": "Discover the top sci-fi thrillers of 2026",
        "link": "/blog.html?id=2026-04-18-sci-fi-thrillers"
    },
    {
        "id": "2026-04-17-k-dramas",
        "date": "2026-04-17",
        "title": "K-Drama Frenzy",
        "category": "korean",
        "excerpt": "Top K-Drama picks with expert analysis",
        "link": "/blog.html?id=2026-04-17-k-dramas"
    },
    {
        "id": "2026-04-17-sci-fi-thrillers",
        "date": "2026-04-17",
        "title": "5 Sci-Fi Thrillers",
        "category": "movies",
        "excerpt": "Explore 5 sci-fi movies with action, suspense, and plot twists",
        "link": "/blog.html?id=2026-04-17-sci-fi-thrillers"
    },
    {
        "id": "2026-04-16-k-dramas",
        "date": "2026-04-16",
        "title": "K-Drama Frenzy",
        "category": "korean",
        "excerpt": "Discover the latest K-Drama hits",
        "link": "/blog.html?id=2026-04-16-k-dramas"
    },
    {
        "id": "2026-04-16-sci-fi-thrillers",
        "date": "2026-04-16",
        "title": "Sci-Fi Thrillers 2026",
        "category": "movies",
        "excerpt": "Explore top sci-fi thrillers of 2026",
        "link": "/blog.html?id=2026-04-16-sci-fi-thrillers"
    },
    {
        "id": "2026-04-15-k-dramas",
        "date": "2026-04-15",
        "title": "K-Drama Frenzy",
        "category": "korean",
        "excerpt": "Discover top K-Dramas",
        "link": "/blog.html?id=2026-04-15-k-dramas"
    },
    {
        "id": "2026-04-15-sci-fi-thrillers",
        "date": "2026-04-15",
        "title": "5 Sci-Fi Thrillers",
        "category": "movies",
        "excerpt": "Buckle up for epic sci-fi thrillers",
        "link": "/blog.html?id=2026-04-15-sci-fi-thrillers"
    },
    {
        "id": "2026-04-10-k-dramas-polished",
        "date": "2026-04-10",
        "title": "Heartstrings and High Stakes: Why 2024's K-Dramas are Dominating Screens",
        "category": "korean",
        "excerpt": "From time-slip romances to high-stakes legal battles, Korean dramas are pushing boundaries in 2024. Here's why you can't stop watching.",
        "link": "/blog.html?id=2026-04-10-k-dramas-polished"
    },
    {
        "id": "2026-04-10-sci-fi-thrillers-FINAL",
        "date": "2026-04-10",
        "title": "The Next Wave of Edge‑of‑Your‑Seat Thrillers Set to Dominate 2025",
        "category": "movies",
        "excerpt": "From surveillance conspiracies to deadly game shows, a fresh batch of high‑octane thrillers is gearing up to hit screens in 2025.",
        "link": "/blog.html?id=2026-04-10-sci-fi-thrillers-FINAL"
    },
    {
        "id": "2026-04-10-welcome",
        "date": "2026-04-10",
        "title": "Welcome to the PickMyBinge Lab",
        "category": "hidden",
        "excerpt": "Discover how we use AI to find you the perfect movie without the endless scroll.",
        "link": "/blog.html?id=2026-04-10-welcome"
    }
]